agentsjson/integrations/__init__.py
agentsjson/integrations/giphy/__init__.py
agentsjson/integrations/giphy/giphy_client/__init__.py
agentsjson/integrations/giphy/giphy_client/api/__init__.py
agentsjson/integrations/giphy/giphy_client/api/default_api.py
agentsjson/integrations/giphy/giphy_client/api_client.py
agentsjson/integrations/giphy/giphy_client/configuration.py
agentsjson/integrations/giphy/giphy_client/models/__init__.py
agentsjson/integrations/giphy/giphy_client/models/all_of_emoji_response_data_items.py
agentsjson/integrations/giphy/giphy_client/models/all_ofinline_response2003_data_items.py
agentsjson/integrations/giphy/giphy_client/models/analytics_object.py
agentsjson/integrations/giphy/giphy_client/models/autocomplete_response.py
agentsjson/integrations/giphy/giphy_client/models/autocomplete_response_data.py
agentsjson/integrations/giphy/giphy_client/models/categories_response.py
agentsjson/integrations/giphy/giphy_client/models/categories_response_data.py
agentsjson/integrations/giphy/giphy_client/models/categories_response_subcategories.py
agentsjson/integrations/giphy/giphy_client/models/category_object.py
agentsjson/integrations/giphy/giphy_client/models/channel_object.py
agentsjson/integrations/giphy/giphy_client/models/channel_search_response.py
agentsjson/integrations/giphy/giphy_client/models/channel_search_response_data.py
agentsjson/integrations/giphy/giphy_client/models/emoji_object.py
agentsjson/integrations/giphy/giphy_client/models/emoji_response.py
agentsjson/integrations/giphy/giphy_client/models/emoji_response_pagination.py
agentsjson/integrations/giphy/giphy_client/models/gif_object.py
agentsjson/integrations/giphy/giphy_client/models/gif_object_analytics.py
agentsjson/integrations/giphy/giphy_client/models/gif_object_analytics_onclick.py
agentsjson/integrations/giphy/giphy_client/models/gif_object_analytics_onload.py
agentsjson/integrations/giphy/giphy_client/models/gif_object_analytics_onsent.py
agentsjson_integrations-0.1.0.dist-info/METADATA
agentsjson_integrations-0.1.0.dist-info/WHEEL
agentsjson_integrations-0.1.0.dist-info/RECORD
