Metadata-Version: 2.3
Name: agentsjson-integrations
Version: 0.1.0
Summary: Integration modules for Agents.json Python implementation
License: Apache-2.0
Author: Wildcard AI
Author-email: info@wildcard.ai
Requires-Python: >=3.8,<4.0
Classifier: License :: OSI Approved :: Apache Software License
Classifier: Programming Language :: Python :: 3
Classifier: Programming Language :: Python :: 3.8
Classifier: Programming Language :: Python :: 3.9
Classifier: Programming Language :: Python :: 3.10
Classifier: Programming Language :: Python :: 3.11
Classifier: Programming Language :: Python :: 3.12
Classifier: Programming Language :: Python :: 3.13
Provides-Extra: all
Provides-Extra: giphy
Provides-Extra: twitter
